dify_dataset_sdk/__init__.py
dify_dataset_sdk/_base.py
dify_dataset_sdk/_exceptions.py
dify_dataset_sdk/client.py
dify_dataset_sdk/py.typed
dify_dataset_sdk/datasets/__init__.py
dify_dataset_sdk/datasets/client.py
dify_dataset_sdk/datasets/models.py
dify_dataset_sdk/documents/__init__.py
dify_dataset_sdk/documents/client.py
dify_dataset_sdk/documents/models.py
dify_dataset_sdk/metadata/__init__.py
dify_dataset_sdk/metadata/client.py
dify_dataset_sdk/metadata/models.py
dify_dataset_sdk/models_api/__init__.py
dify_dataset_sdk/models_api/client.py
dify_dataset_sdk/models_api/models.py
dify_dataset_sdk/segments/__init__.py
dify_dataset_sdk/segments/client.py
dify_dataset_sdk/segments/models.py
dify_dataset_sdk/tags/__init__.py
dify_dataset_sdk/tags/client.py
dify_dataset_sdk/tags/models.py
dify_dataset_sdk-0.5.0.dist-info/METADATA
dify_dataset_sdk-0.5.0.dist-info/WHEEL
dify_dataset_sdk-0.5.0.dist-info/RECORD
